{
  "smart-random-note:open-random-note": [
    {
      "modifiers": [
        "Alt",
        "Mod"
      ],
      "key": "R"
    }
  ],
  "smart-random-note:open-tagged-random-note": [
    {
      "modifiers": [
        "Alt",
        "Mod",
        "Shift"
      ],
      "key": "R"
    }
  ],
  "templater-obsidian:create-new-note-from-template": [
    {
      "modifiers": [
        "Alt"
      ],
      "key": "N"
    }
  ],
  "templater-obsidian:jump-to-next-cursor-location": [
    {
      "modifiers": [
        "Alt"
      ],
      "key": "Tab"
    }
  ],
  "file-explorer:reveal-active-file": [
    {
      "modifiers": [
        "Ctrl"
      ],
      "key": "F"
    }
  ],
  "editor:insert-wikilink": [
    {
      "modifiers": [
        "Mod",
        "Shift"
      ],
      "key": "K"
    }
  ],
  "editor:toggle-highlight": [
    {
      "modifiers": [
        "Ctrl"
      ],
      "key": "H"
    }
  ],
  "obsidian-admonition:insert-callout": [
    {
      "modifiers": [
        "Ctrl",
        "Shift"
      ],
      "key": "C"
    }
  ],
  "editor-commands-remap:indent-more": [],
  "editor-commands-remap:indent-less": [],
  "editor-commands-remap:toggle-fold": [],
  "editor-commands-remap:new-line-indent": [
    {
      "modifiers": [
        "Shift"
      ],
      "key": "Enter"
    }
  ],
  "maximise-active-pane-obsidian:maximise-active-pane": [],
  "cycle-through-panes:cycle-through-panes-reverse": [
    {
      "modifiers": [
        "Alt",
        "Shift"
      ],
      "key": "."
    }
  ],
  "file-explorer:new-file-in-new-pane": [],
  "cycle-through-panes:cycle-through-panes": [
    {
      "modifiers": [
        "Alt"
      ],
      "key": ","
    }
  ],
  "workspace:split-vertical": [
    {
      "modifiers": [
        "Mod",
        "Shift"
      ],
      "key": "R"
    }
  ],
  "workspace:copy-path": [
    {
      "modifiers": [
        "Alt",
        "Mod"
      ],
      "key": "P"
    }
  ],
  "daily-notes": [
    {
      "modifiers": [
        "Mod",
        "Shift"
      ],
      "key": "T"
    }
  ],
  "table-editor-obsidian:table-control-bar": [],
  "obsidian-excalidraw-plugin:insert-link-to-element": [],
  "workspace:undo-close-pane": [],
  "app:toggle-left-sidebar": [
    {
      "modifiers": [
        "Ctrl"
      ],
      "key": "L"
    }
  ],
  "app:toggle-right-sidebar": [
    {
      "modifiers": [
        "Ctrl"
      ],
      "key": "R"
    }
  ],
  "omnisearch:show-modal": [
    {
      "modifiers": [
        "Mod",
        "Shift"
      ],
      "key": "O"
    }
  ],
  "dbfolder:active-database-folder-add-new-row": [],
  "obsidian-focus-mode:toggle-focus-mode": [
    {
      "modifiers": [
        "Mod",
        "Shift"
      ],
      "key": "P"
    }
  ],
  "obsidian-focus-mode:toggle-super-focus-mode": [
    {
      "modifiers": [
        "Alt",
        "Mod",
        "Shift"
      ],
      "key": "P"
    }
  ],
  "obsidian-advanced-slides:reload-advanced-slides-preview": [],
  "obsidian-shellcommands:shell-command-lgxhp8kktq": [
    {
      "modifiers": [
        "Alt",
        "Ctrl",
        "Mod"
      ],
      "key": "M"
    }
  ],
  "templater-obsidian:S01 Personal/060-069 Utilities/64 Templates/TPL Literature Note.md": [
    {
      "modifiers": [
        "Alt",
        "Mod",
        "Shift"
      ],
      "key": "L"
    }
  ],
  "templater-obsidian:S01 Personal/060-069 Utilities/64 Templates/TPL Permanent Note.md": [
    {
      "modifiers": [
        "Alt",
        "Mod",
        "Shift"
      ],
      "key": "S"
    }
  ],
  "templater-obsidian:S01 Personal/060-069 Utilities/64 Templates/TPL Fleeting Note.md": [
    {
      "modifiers": [
        "Alt",
        "Mod",
        "Shift"
      ],
      "key": "F"
    }
  ],
  "window:zoom-out": [
    {
      "modifiers": [
        "Mod"
      ],
      "key": "-"
    }
  ],
  "window:zoom-in": [
    {
      "modifiers": [
        "Mod"
      ],
      "key": "="
    }
  ],
  "window:reset-zoom": [
    {
      "modifiers": [
        "Mod"
      ],
      "key": "0"
    }
  ],
  "editor:swap-line-up": [
    {
      "modifiers": [
        "Mod"
      ],
      "key": "ArrowUp"
    }
  ],
  "editor:swap-line-down": [
    {
      "modifiers": [
        "Mod"
      ],
      "key": "ArrowDown"
    }
  ],
  "editor:toggle-bullet-list": [
    {
      "modifiers": [
        "Mod"
      ],
      "key": "3"
    }
  ],
  "workspace:goto-tab-3": [],
  "quickadd:runQuickAdd": [
    {
      "modifiers": [
        "Ctrl",
        "Shift"
      ],
      "key": "S"
    }
  ],
  "folder-note-core:link-to-parent-folder": [
    {
      "modifiers": [
        "Mod",
        "Shift"
      ],
      "key": "U"
    }
  ],
  "obsidian-excalidraw-plugin:insert-link": [],
  "app:delete-file": [
    {
      "modifiers": [
        "Mod",
        "Shift"
      ],
      "key": "D"
    }
  ]
}